coretex/__init__.py
coretex/_folder_manager.py
coretex/_logger.py
coretex/cache.py
coretex/functions.py
coretex/py.typed
coretex/statistics.py
coretex/_task/__init__.py
coretex/_task/base_callback.py
coretex/_task/current_task_run.py
coretex/_task/initialization.py
coretex/_task/process_utils.py
coretex/_task/local/__init__.py
coretex/_task/local/task_config.py
coretex/_task/remote/__init__.py
coretex/_task/remote/remote.py
coretex/_task/run_logger/__init__.py
coretex/_task/run_logger/run_logger.py
coretex/_task/run_logger/upload_worker.py
coretex/_task/worker/__init__.py
coretex/_task/worker/artifacts.py
coretex/_task/worker/metrics.py
coretex/_task/worker/utils.py
coretex/_task/worker/worker.py
coretex/bioinformatics/__init__.py
coretex/bioinformatics/utils.py
coretex/bioinformatics/ctx_qiime2/__init__.py
coretex/bioinformatics/ctx_qiime2/utils.py
coretex/bioinformatics/sequence_alignment/__init__.py
coretex/cli/__init__.py
coretex/cli/main.py
coretex/cli/commands/__init__.py
coretex/cli/commands/login.py
coretex/cli/commands/model.py
coretex/cli/commands/node.py
coretex/cli/commands/project.py
coretex/cli/commands/task.py
coretex/cli/modules/__init__.py
coretex/cli/modules/cron.py
coretex/cli/modules/intercept.py
coretex/cli/modules/node.py
coretex/cli/modules/project_utils.py
coretex/cli/modules/ui.py
coretex/cli/modules/update.py
coretex/cli/modules/user.py
coretex/cli/modules/utils.py
coretex/cli/resources/__init__.py
coretex/cli/resources/resources.py
coretex/cli/resources/update_script_template.sh
coretex/codable/__init__.py
coretex/codable/codable.py
coretex/codable/descriptor.py
coretex/configuration/__init__.py
coretex/configuration/base.py
coretex/configuration/config_defaults.py
coretex/configuration/node.py
coretex/configuration/user.py
coretex/configuration/utils.py
coretex/cryptography/__init__.py
coretex/cryptography/random_generator.py
coretex/cryptography/rsa.py
coretex/cryptography/utils.py
coretex/cryptography/aes/__init__.py
coretex-1.0.187.dist-info/LICENSE
coretex-1.0.187.dist-info/METADATA
coretex-1.0.187.dist-info/WHEEL
coretex-1.0.187.dist-info/entry_points.txt
coretex-1.0.187.dist-info/top_level.txt
coretex-1.0.187.dist-info/RECORD
