Metadata-Version: 2.1
Name: coretex
Version: 1.0.187
Summary: A package for AI experiment tracking, infrastructure and dataset management using Coretex.ai platform.
Author-email: Duško Mirković <dmirkovic@coretex.ai>
Maintainer-email: Duško Mirković <dmirkovic@coretex.ai>, Igor Perić <igor@coretex.ai>, Jovica Zarić <jzaric@coretex.ai>, Darko Zarić <dzaric@coretex.ai>, Bogdan Tintor <btintor@coretex.ai>, Alex Maslennikov <alex@coretex.ai>
Project-URL: Homepage, https://coretex.ai
Project-URL: Documentation, https://docs.coretex.ai/
Project-URL: Python API, https://coretexpylib.coretex.ai/
Project-URL: Source, https://github.com/coretex-ai/coretexpylib
Classifier: Programming Language :: Python :: 3
Classifier: License :: OSI Approved :: GNU Affero General Public License v3 or later (AGPLv3+)
Classifier: Operating System :: OS Independent
Requires-Python: >=3.8
License-File: LICENSE
Requires-Dist: requests >=2.32.3
Requires-Dist: inflection >=0.5.1
Requires-Dist: pillow >=10.2.0
Requires-Dist: numpy <2
Requires-Dist: scikit-image >=0.21.0
Requires-Dist: shapely ==2.0.5
Requires-Dist: typed-argument-parser >=1.10.1
Requires-Dist: typing-extensions >=4.12.2
Requires-Dist: psutil >=6.0.0
Requires-Dist: py3nvml >=0.2.7
Requires-Dist: watchdog >=4.0.2
Requires-Dist: gitpython >=3.1.43
Requires-Dist: pyyaml ==6.0.2
Requires-Dist: click >=8.1.7
Requires-Dist: tabulate >=0.9.0
Requires-Dist: inquirer >=3.4.0
Requires-Dist: cryptography >=43.0.0
Requires-Dist: pycryptodome >=3.20.0
Requires-Dist: onnxruntime >=1.16.3
Requires-Dist: ezkl >=12.0.1
